[
  {
    "uuid": "system",
    "name": "系统管理",
    "children": [
      {
        "uuid": "system.config",
        "name": "系统配置",
        "children": [
          {
            "uuid": "system.config.MenuList",
            "name": "菜单设置",
            "pagePath": "/system/config/MenuList"
          },
          {
            "uuid": "system.config.RoleList",
            "name": "角色管理",
            "pagePath": "/system/config/RoleList",
            "subPages": [
              {
                "uuid": "system.config.RoleDetail",
                "name": "角色详情",
                "pagePath": "/system/config/RoleDetail"
              },
              {
                "uuid": "system.config.RoleMember",
                "name": "角色成员",
                "pagePath": "/system/config/RoleMember"
              }
            ],
            "permis": [
              {
                "uuid": "system.config.RoleList.edit",
                "name": "角色编辑"
              },
              {
                "uuid": "system.config.RoleList.remove",
                "name": "角色删除"
              }
            ]
          },
          {
            "uuid": "system.config.UserList",
            "name": "用户管理",
            "pagePath": "/system/config/UserList",
            "subPages": [
              {
                "uuid": "system.config.UserDetail",
                "name": "用户详情",
                "pagePath": "/system/config/UserDetail"
              }
            ],
            "permis": [
              {
                "uuid": "system.config.UserList.remove",
                "name": "用户删除"
              }
            ]
          }
        ]
      }
    ]
  },
  {
    "uuid": "demo",
    "name": "演示系统",
    "children": [
      {
        "uuid": "demo.base.BaseForm",
        "name": "基本表单",
        "pagePath": "/demo/base/BaseForm"
      },
      {
        "uuid": "demo.base.AdvanceForm",
        "name": "高级表单",
        "pagePath": "/demo/base/AdvanceForm"
      }
    ]
  }
]
